our_groceries_client
