Metadata-Version: 1.0
Name: our-groceries-client
Version: 0.1.2
Summary: An interface to manipulating items on an OurGroceries.com list
Home-page: https://github.com/smpickett/our_groceries_client
Author: smpickett
Author-email: smpickett@gmail.com
License: MIT
Keywords: grocery list
Platform: UNKNOWN
